{".class":"MypyFile","_fullname":"flask_limiter.constants","future_import_flags":["annotations"],"is_partial_stub_package":false,"is_stub":false,"names":{".class":"SymbolTable","ConfigVars":{".class":"SymbolTableNode","kind":"Gdef","node":{".class":"TypeInfo","_promote":[],"abstract_attributes":[],"alt_promote":null,"bases":["builtins.object"],"dataclass_transform_spec":null,"declared_metaclass":null,"defn":{".class":"ClassDef","fullname":"flask_limiter.constants.ConfigVars","name":"ConfigVars","type_vars":[]},"deletable_attributes":[],"deprecated":null,"flags":[],"fullname":"flask_limiter.constants.ConfigVars","has_param_spec_type":false,"metaclass_type":null,"metadata":{},"module_name":"flask_limiter.constants","mro":["flask_limiter.constants.ConfigVars","builtins.object"],"names":{".class":"SymbolTable","APPLICATION_LIMITS":{".class":"SymbolTableNode","kind":"Mdef","node":{".class":"Var","flags":["is_initialized_in_class","is_ready","is_inferred","has_explicit_value"],"fullname":"flask_limiter.constants.ConfigVars.APPLICATION_LIMITS","name":"APPLICATION_LIMITS","type":"builtins.str"}},"APPLICATION_LIMITS_COST":{".class":"SymbolTableNode","kind":"Mdef","node":{".class":"Var","flags":["is_initialized_in_class","is_ready","is_inferred","has_explicit_value"],"fullname":"flask_limiter.constants.ConfigVars.APPLICATION_LIMITS_COST","name":"APPLICATION_LIMITS_COST","type":"builtins.str"}},"APPLICATION_LIMITS_DEDUCT_WHEN":{".class":"SymbolTableNode","kind":"Mdef","node":{".class":"Var","flags":["is_initialized_in_class","is_ready","is_inferred","has_explicit_value"],"fullname":"flask_limiter.constants.ConfigVars.APPLICATION_LIMITS_DEDUCT_WHEN","name":"APPLICATION_LIMITS_DEDUCT_WHEN","type":"builtins.str"}},"APPLICATION_LIMITS_EXEMPT_WHEN":{".class":"SymbolTableNode","kind":"Mdef","node":{".class":"Var","flags":["is_initialized_in_class","is_ready","is_inferred","has_explicit_value"],"fullname":"flask_limiter.constants.ConfigVars.APPLICATION_LIMITS_EXEMPT_WHEN","name":"APPLICATION_LIMITS_EXEMPT_WHEN","type":"builtins.str"}},"APPLICATION_LIMITS_PER_METHOD":{".class":"SymbolTableNode","kind":"Mdef","node":{".class":"Var","flags":["is_initialized_in_class","is_ready","is_inferred","has_explicit_value"],"fullname":"flask_limiter.constants.ConfigVars.APPLICATION_LIMITS_PER_METHOD","name":"APPLICATION_LIMITS_PER_METHOD","type":"builtins.str"}},"DEFAULT_LIMITS":{".class":"SymbolTableNode","kind":"Mdef","node":{".class":"Var","flags":["is_initialized_in_class","is_ready","is_inferred","has_explicit_value"],"fullname":"flask_limiter.constants.ConfigVars.DEFAULT_LIMITS","name":"DEFAULT_LIMITS","type":"builtins.str"}},"DEFAULT_LIMITS_COST":{".class":"SymbolTableNode","kind":"Mdef","node":{".class":"Var","flags":["is_initialized_in_class","is_ready","is_inferred","has_explicit_value"],"fullname":"flask_limiter.constants.ConfigVars.DEFAULT_LIMITS_COST","name":"DEFAULT_LIMITS_COST","type":"builtins.str"}},"DEFAULT_LIMITS_DEDUCT_WHEN":{".class":"SymbolTableNode","kind":"Mdef","node":{".class":"Var","flags":["is_initialized_in_class","is_ready","is_inferred","has_explicit_value"],"fullname":"flask_limiter.constants.ConfigVars.DEFAULT_LIMITS_DEDUCT_WHEN","name":"DEFAULT_LIMITS_DEDUCT_WHEN","type":"builtins.str"}},"DEFAULT_LIMITS_EXEMPT_WHEN":{".class":"SymbolTableNode","kind":"Mdef","node":{".class":"Var","flags":["is_initialized_in_class","is_ready","is_inferred","has_explicit_value"],"fullname":"flask_limiter.constants.ConfigVars.DEFAULT_LIMITS_EXEMPT_WHEN","name":"DEFAULT_LIMITS_EXEMPT_WHEN","type":"builtins.str"}},"DEFAULT_LIMITS_PER_METHOD":{".class":"SymbolTableNode","kind":"Mdef","node":{".class":"Var","flags":["is_initialized_in_class","is_ready","is_inferred","has_explicit_value"],"fullname":"flask_limiter.constants.ConfigVars.DEFAULT_LIMITS_PER_METHOD","name":"DEFAULT_LIMITS_PER_METHOD","type":"builtins.str"}},"ENABLED":{".class":"SymbolTableNode","kind":"Mdef","node":{".class":"Var","flags":["is_initialized_in_class","is_ready","is_inferred","has_explicit_value"],"fullname":"flask_limiter.constants.ConfigVars.ENABLED","name":"ENABLED","type":"builtins.str"}},"FAIL_ON_FIRST_BREACH":{".class":"SymbolTableNode","kind":"Mdef","node":{".class":"Var","flags":["is_initialized_in_class","is_ready","is_inferred","has_explicit_value"],"fullname":"flask_limiter.constants.ConfigVars.FAIL_ON_FIRST_BREACH","name":"FAIL_ON_FIRST_BREACH","type":"builtins.str"}},"HEADERS_ENABLED":{".class":"SymbolTableNode","kind":"Mdef","node":{".class":"Var","flags":["is_initialized_in_class","is_ready","is_inferred","has_explicit_value"],"fullname":"flask_limiter.constants.ConfigVars.HEADERS_ENABLED","name":"HEADERS_ENABLED","type":"builtins.str"}},"HEADER_LIMIT":{".class":"SymbolTableNode","kind":"Mdef","node":{".class":"Var","flags":["is_initialized_in_class","is_ready","is_inferred","has_explicit_value"],"fullname":"flask_limiter.constants.ConfigVars.HEADER_LIMIT","name":"HEADER_LIMIT","type":"builtins.str"}},"HEADER_REMAINING":{".class":"SymbolTableNode","kind":"Mdef","node":{".class":"Var","flags":["is_initialized_in_class","is_ready","is_inferred","has_explicit_value"],"fullname":"flask_limiter.constants.ConfigVars.HEADER_REMAINING","name":"HEADER_REMAINING","type":"builtins.str"}},"HEADER_RESET":{".class":"SymbolTableNode","kind":"Mdef","node":{".class":"Var","flags":["is_initialized_in_class","is_ready","is_inferred","has_explicit_value"],"fullname":"flask_limiter.constants.ConfigVars.HEADER_RESET","name":"HEADER_RESET","type":"builtins.str"}},"HEADER_RETRY_AFTER":{".class":"SymbolTableNode","kind":"Mdef","node":{".class":"Var","flags":["is_initialized_in_class","is_ready","is_inferred","has_explicit_value"],"fullname":"flask_limiter.constants.ConfigVars.HEADER_RETRY_AFTER","name":"HEADER_RETRY_AFTER","type":"builtins.str"}},"HEADER_RETRY_AFTER_VALUE":{".class":"SymbolTableNode","kind":"Mdef","node":{".class":"Var","flags":["is_initialized_in_class","is_ready","is_inferred","has_explicit_value"],"fullname":"flask_limiter.constants.ConfigVars.HEADER_RETRY_AFTER_VALUE","name":"HEADER_RETRY_AFTER_VALUE","type":"builtins.str"}},"IN_MEMORY_FALLBACK":{".class":"SymbolTableNode","kind":"Mdef","node":{".class":"Var","flags":["is_initialized_in_class","is_ready","is_inferred","has_explicit_value"],"fullname":"flask_limiter.constants.ConfigVars.IN_MEMORY_FALLBACK","name":"IN_MEMORY_FALLBACK","type":"builtins.str"}},"IN_MEMORY_FALLBACK_ENABLED":{".class":"SymbolTableNode","kind":"Mdef","node":{".class":"Var","flags":["is_initialized_in_class","is_ready","is_inferred","has_explicit_value"],"fullname":"flask_limiter.constants.ConfigVars.IN_MEMORY_FALLBACK_ENABLED","name":"IN_MEMORY_FALLBACK_ENABLED","type":"builtins.str"}},"KEY_FUNC":{".class":"SymbolTableNode","kind":"Mdef","node":{".class":"Var","flags":["is_initialized_in_class","is_ready","is_inferred","has_explicit_value"],"fullname":"flask_limiter.constants.ConfigVars.KEY_FUNC","name":"KEY_FUNC","type":"builtins.str"}},"KEY_PREFIX":{".class":"SymbolTableNode","kind":"Mdef","node":{".class":"Var","flags":["is_initialized_in_class","is_ready","is_inferred","has_explicit_value"],"fullname":"flask_limiter.constants.ConfigVars.KEY_PREFIX","name":"KEY_PREFIX","type":"builtins.str"}},"META_LIMITS":{".class":"SymbolTableNode","kind":"Mdef","node":{".class":"Var","flags":["is_initialized_in_class","is_ready","is_inferred","has_explicit_value"],"fullname":"flask_limiter.constants.ConfigVars.META_LIMITS","name":"META_LIMITS","type":"builtins.str"}},"ON_BREACH":{".class":"SymbolTableNode","kind":"Mdef","node":{".class":"Var","flags":["is_initialized_in_class","is_ready","is_inferred","has_explicit_value"],"fullname":"flask_limiter.constants.ConfigVars.ON_BREACH","name":"ON_BREACH","type":"builtins.str"}},"ON_META_BREACH":{".class":"SymbolTableNode","kind":"Mdef","node":{".class":"Var","flags":["is_initialized_in_class","is_ready","is_inferred","has_explicit_value"],"fullname":"flask_limiter.constants.ConfigVars.ON_META_BREACH","name":"ON_META_BREACH","type":"builtins.str"}},"REQUEST_IDENTIFIER":{".class":"SymbolTableNode","kind":"Mdef","node":{".class":"Var","flags":["is_initialized_in_class","is_ready","is_inferred","has_explicit_value"],"fullname":"flask_limiter.constants.ConfigVars.REQUEST_IDENTIFIER","name":"REQUEST_IDENTIFIER","type":"builtins.str"}},"STORAGE_OPTIONS":{".class":"SymbolTableNode","kind":"Mdef","node":{".class":"Var","flags":["is_initialized_in_class","is_ready","is_inferred","has_explicit_value"],"fullname":"flask_limiter.constants.ConfigVars.STORAGE_OPTIONS","name":"STORAGE_OPTIONS","type":"builtins.str"}},"STORAGE_URI":{".class":"SymbolTableNode","kind":"Mdef","node":{".class":"Var","flags":["is_initialized_in_class","is_ready","is_inferred","has_explicit_value"],"fullname":"flask_limiter.constants.ConfigVars.STORAGE_URI","name":"STORAGE_URI","type":"builtins.str"}},"STRATEGY":{".class":"SymbolTableNode","kind":"Mdef","node":{".class":"Var","flags":["is_initialized_in_class","is_ready","is_inferred","has_explicit_value"],"fullname":"flask_limiter.constants.ConfigVars.STRATEGY","name":"STRATEGY","type":"builtins.str"}},"SWALLOW_ERRORS":{".class":"SymbolTableNode","kind":"Mdef","node":{".class":"Var","flags":["is_initialized_in_class","is_ready","is_inferred","has_explicit_value"],"fullname":"flask_limiter.constants.ConfigVars.SWALLOW_ERRORS","name":"SWALLOW_ERRORS","type":"builtins.str"}}},"self_type":{".class":"TypeVarType","default":{".class":"AnyType","missing_import_name":null,"source_any":null,"type_of_any":4},"fullname":"flask_limiter.constants.ConfigVars.Self","id":0,"name":"Self","namespace":"","upper_bound":"flask_limiter.constants.ConfigVars","values":[],"variance":0},"slots":null,"tuple_type":null,"type_vars":[],"typeddict_type":null}},"ExemptionScope":{".class":"SymbolTableNode","kind":"Gdef","node":{".class":"TypeInfo","_promote":[],"abstract_attributes":[],"alt_promote":null,"bases":["enum.Flag"],"dataclass_transform_spec":null,"declared_metaclass":null,"defn":{".class":"ClassDef","fullname":"flask_limiter.constants.ExemptionScope","name":"ExemptionScope","type_vars":[]},"deletable_attributes":[],"deprecated":null,"flags":["is_enum"],"fullname":"flask_limiter.constants.ExemptionScope","has_param_spec_type":false,"metaclass_type":"enum.EnumMeta","metadata":{},"module_name":"flask_limiter.constants","mro":["flask_limiter.constants.ExemptionScope","enum.Flag","enum.Enum","builtins.object"],"names":{".class":"SymbolTable","ANCESTORS":{".class":"SymbolTableNode","kind":"Mdef","node":{".class":"Var","flags":["is_initialized_in_class","is_final","is_inferred","has_explicit_value"],"fullname":"flask_limiter.constants.ExemptionScope.ANCESTORS","name":"ANCESTORS","type":"enum.auto"}},"APPLICATION":{".class":"SymbolTableNode","kind":"Mdef","node":{".class":"Var","flags":["is_initialized_in_class","is_final","is_inferred","has_explicit_value"],"fullname":"flask_limiter.constants.ExemptionScope.APPLICATION","name":"APPLICATION","type":"enum.auto"}},"DEFAULT":{".class":"SymbolTableNode","kind":"Mdef","node":{".class":"Var","flags":["is_initialized_in_class","is_final","is_inferred","has_explicit_value"],"fullname":"flask_limiter.constants.ExemptionScope.DEFAULT","name":"DEFAULT","type":"enum.auto"}},"DESCENDENTS":{".class":"SymbolTableNode","kind":"Mdef","node":{".class":"Var","flags":["is_initialized_in_class","is_final","is_inferred","has_explicit_value"],"fullname":"flask_limiter.constants.ExemptionScope.DESCENDENTS","name":"DESCENDENTS","type":"enum.auto"}},"META":{".class":"SymbolTableNode","kind":"Mdef","node":{".class":"Var","flags":["is_initialized_in_class","is_final","is_inferred","has_explicit_value"],"fullname":"flask_limiter.constants.ExemptionScope.META","name":"META","type":"enum.auto"}},"NONE":{".class":"SymbolTableNode","kind":"Mdef","node":{".class":"Var","flags":["is_initialized_in_class","is_final","is_ready","is_inferred","has_explicit_value"],"fullname":"flask_limiter.constants.ExemptionScope.NONE","name":"NONE","type":{".class":"Instance","args":[],"extra_attrs":null,"last_known_value":{".class":"LiteralType","fallback":"builtins.int","value":0},"type_ref":"builtins.int"}}}},"self_type":{".class":"TypeVarType","default":{".class":"AnyType","missing_import_name":null,"source_any":null,"type_of_any":4},"fullname":"flask_limiter.constants.ExemptionScope.Self","id":0,"name":"Self","namespace":"","upper_bound":"flask_limiter.constants.ExemptionScope","values":[],"variance":0},"slots":null,"tuple_type":null,"type_vars":[],"typeddict_type":null}},"HeaderNames":{".class":"SymbolTableNode","kind":"Gdef","node":{".class":"TypeInfo","_promote":[],"abstract_attributes":[],"alt_promote":null,"bases":["enum.Enum"],"dataclass_transform_spec":null,"declared_metaclass":null,"defn":{".class":"ClassDef","fullname":"flask_limiter.constants.HeaderNames","name":"HeaderNames","type_vars":[]},"deletable_attributes":[],"deprecated":null,"flags":["is_enum"],"fullname":"flask_limiter.constants.HeaderNames","has_param_spec_type":false,"metaclass_type":"enum.EnumMeta","metadata":{},"module_name":"flask_limiter.constants","mro":["flask_limiter.constants.HeaderNames","enum.Enum","builtins.object"],"names":{".class":"SymbolTable","LIMIT":{".class":"SymbolTableNode","kind":"Mdef","node":{".class":"Var","flags":["is_initialized_in_class","is_final","is_ready","is_inferred","has_explicit_value"],"fullname":"flask_limiter.constants.HeaderNames.LIMIT","name":"LIMIT","type":{".class":"Instance","args":[],"extra_attrs":null,"last_known_value":{".class":"LiteralType","fallback":"builtins.str","value":"X-RateLimit-Limit"},"type_ref":"builtins.str"}}},"REMAINING":{".class":"SymbolTableNode","kind":"Mdef","node":{".class":"Var","flags":["is_initialized_in_class","is_final","is_ready","is_inferred","has_explicit_value"],"fullname":"flask_limiter.constants.HeaderNames.REMAINING","name":"REMAINING","type":{".class":"Instance","args":[],"extra_attrs":null,"last_known_value":{".class":"LiteralType","fallback":"builtins.str","value":"X-RateLimit-Remaining"},"type_ref":"builtins.str"}}},"RESET":{".class":"SymbolTableNode","kind":"Mdef","node":{".class":"Var","flags":["is_initialized_in_class","is_final","is_ready","is_inferred","has_explicit_value"],"fullname":"flask_limiter.constants.HeaderNames.RESET","name":"RESET","type":{".class":"Instance","args":[],"extra_attrs":null,"last_known_value":{".class":"LiteralType","fallback":"builtins.str","value":"X-RateLimit-Reset"},"type_ref":"builtins.str"}}},"RETRY_AFTER":{".class":"SymbolTableNode","kind":"Mdef","node":{".class":"Var","flags":["is_initialized_in_class","is_final","is_ready","is_inferred","has_explicit_value"],"fullname":"flask_limiter.constants.HeaderNames.RETRY_AFTER","name":"RETRY_AFTER","type":{".class":"Instance","args":[],"extra_attrs":null,"last_known_value":{".class":"LiteralType","fallback":"builtins.str","value":"Retry-After"},"type_ref":"builtins.str"}}}},"self_type":{".class":"TypeVarType","default":{".class":"AnyType","missing_import_name":null,"source_any":null,"type_of_any":4},"fullname":"flask_limiter.constants.HeaderNames.Self","id":0,"name":"Self","namespace":"","upper_bound":"flask_limiter.constants.HeaderNames","values":[],"variance":0},"slots":null,"tuple_type":null,"type_vars":[],"typeddict_type":null}},"MAX_BACKEND_CHECKS":{".class":"SymbolTableNode","kind":"Gdef","node":{".class":"Var","flags":["is_ready","is_inferred","has_explicit_value"],"fullname":"flask_limiter.constants.MAX_BACKEND_CHECKS","name":"MAX_BACKEND_CHECKS","type":"builtins.int"}},"__annotations__":{".class":"SymbolTableNode","kind":"Gdef","node":{".class":"Var","flags":["is_ready"],"fullname":"flask_limiter.constants.__annotations__","name":"__annotations__","type":{".class":"Instance","args":["builtins.str",{".class":"AnyType","missing_import_name":null,"source_any":null,"type_of_any":6}],"extra_attrs":null,"type_ref":"builtins.dict"}}},"__doc__":{".class":"SymbolTableNode","kind":"Gdef","node":{".class":"Var","flags":["is_ready"],"fullname":"flask_limiter.constants.__doc__","name":"__doc__","type":"builtins.str"}},"__file__":{".class":"SymbolTableNode","kind":"Gdef","node":{".class":"Var","flags":["is_ready"],"fullname":"flask_limiter.constants.__file__","name":"__file__","type":"builtins.str"}},"__name__":{".class":"SymbolTableNode","kind":"Gdef","node":{".class":"Var","flags":["is_ready"],"fullname":"flask_limiter.constants.__name__","name":"__name__","type":"builtins.str"}},"__package__":{".class":"SymbolTableNode","kind":"Gdef","node":{".class":"Var","flags":["is_ready"],"fullname":"flask_limiter.constants.__package__","name":"__package__","type":"builtins.str"}},"__spec__":{".class":"SymbolTableNode","kind":"Gdef","node":{".class":"Var","flags":["is_ready"],"fullname":"flask_limiter.constants.__spec__","name":"__spec__","type":"_frozen_importlib.ModuleSpec"}},"annotations":{".class":"SymbolTableNode","cross_ref":"__future__.annotations","kind":"Gdef"},"enum":{".class":"SymbolTableNode","cross_ref":"enum","kind":"Gdef"}},"path":"C:\\Users\\Kiaco\\AppData\\Roaming\\Python\\Python314\\site-packages\\flask_limiter\\constants.py"}